outline_ai/__init__.py
outline_ai/main.py
outline_ai/prompts.py
outline_ai-2025.12.22110945.dist-info/METADATA
outline_ai-2025.12.22110945.dist-info/WHEEL
outline_ai-2025.12.22110945.dist-info/top_level.txt
outline_ai-2025.12.22110945.dist-info/RECORD
