Metadata-Version: 2.4
Name: outline-ai
Version: 2025.12.22110945
Summary: outline-ai converts text into structured summaries, proposals, or outlines, automating publication creation with clarity and ease.
Author-email: outline-ai <hi@eugene.plus>
License: MIT
Project-URL: Homepage, https://github.com/chigwell/outline-ai
Requires-Python: >=3.9
Requires-Dist: langchain-llm7>=0.0.0
Requires-Dist: llmatch-messages>=0.0.0
Requires-Dist: langchain-core>=0.3.0
